Workbook

Sheet Top Frequent Customers
A1: Order Count Rank | B1: Customer ID | C1: Customer Name | D1: Order Count | E1: Order Lines | F1: Total Sales ($) | G1: Avg Order Value ($)
A2: =RANK('All Customers'!C2,'All Customers'!$C$2:$C$794) -> 1 | B2: ='All Customers'!A2 -> EP-13915 | C2: ='All Customers'!B2 -> Emily Phan | D2: ='All Customers'!C2 -> 17 | E2: ='All Customers'!D2 -> 31 | F2: ='All Customers'!E2 -> 5478.0608 | G2: ='All Customers'!G2 -> 322.23887
A3: =RANK('All Customers'!C3,'All Customers'!$C$2:$C$794) -> 2 | B3: ='All Customers'!A3 -> ZC-21910 | C3: ='All Customers'!B3 -> Zuschuss Carroll | D3: ='All Customers'!C3 -> 13 | E3: ='All Customers'!D3 -> 31 | F3: ='All Customers'!E3 -> 8025.707 | G3: ='All Customers'!G3 -> 617.36208
A4: =RANK('All Customers'!C4,'All Customers'!$C$2:$C$794) -> 2 | B4: ='All Customers'!A4 -> JE-15745 | C4: ='All Customers'!B4 -> Joel Eaton | D4: ='All Customers'!C4 -> 13 | E4: ='All Customers'!D4 -> 23 | F4: ='All Customers'!E4 -> 6760.815 | G4: ='All Customers'!G4 -> 520.06269
A5: =RANK('All Customers'!C5,'All Customers'!$C$2:$C$794) -> 2 | B5: ='All Customers'!A5 -> SH-19975 | C5: ='All Customers'!B5 -> Sally Hughsby | D5: ='All Customers'!C5 -> 13 | E5: ='All Customers'!D5 -> 29 | F5: ='All Customers'!E5 -> 3406.8395 | G5: ='All Customers'!G5 -> 262.06458
A6: =RANK('All Customers'!C6,'All Customers'!$C$2:$C$794) -> 2 | B6: ='All Customers'!A6 -> CK-12205 | C6: ='All Customers'!B6 -> Chloris Kastensmidt | D6: ='All Customers'!C6 -> 13 | E6: ='All Customers'!D6 -> 32 | F6: ='All Customers'!E6 -> 3154.855 | G6: ='All Customers'!G6 -> 242.68115
A7: =RANK('All Customers'!C7,'All Customers'!$C$2:$C$794) -> 2 | B7: ='All Customers'!A7 -> PG-18820 | C7: ='All Customers'!B7 -> Patrick Gardner | D7: ='All Customers'!C7 -> 13 | E7: ='All Customers'!D7 -> 26 | F7: ='All Customers'!E7 -> 3086.907 | G7: ='All Customers'!G7 -> 237.45438
A8: =RANK('All Customers'!C8,'All Customers'!$C$2:$C$794) -> 2 | B8: ='All Customers'!A8 -> NS-18640 | C8: ='All Customers'!B8 -> Noel Staavos | D8: ='All Customers'!C8 -> 13 | E8: ='All Customers'!D8 -> 26 | F8: ='All Customers'!E8 -> 2964.823 | G8: ='All Customers'!G8 -> 228.06331
A9: =RANK('All Customers'!C9,'All Customers'!$C$2:$C$794) -> 2 | B9: ='All Customers'!A9 -> EA-14035 | C9: ='All Customers'!B9 -> Erin Ashbrook | D9: ='All Customers'!C9 -> 13 | E9: ='All Customers'!D9 -> 25 | F9: ='All Customers'!E9 -> 2846.705 | G9: ='All Customers'!G9 -> 218.97731
A10: =RANK('All Customers'!C10,'All Customers'!$C$2:$C$794) -> 9 | B10: ='All Customers'!A10 -> KL-16645 | C10: ='All Customers'!B10 -> Ken Lonsdale | D10: ='All Customers'!C10 -> 12 | E10: ='All Customers'!D10 -> 29 | F10: ='All Customers'!E10 -> 14175.229 | G10: ='All Customers'!G10 -> 1181.2691
A11: =RANK('All Customers'!C11,'All Customers'!$C$2:$C$794) -> 9 | B11: ='All Customers'!A11 -> CL-12565 | C11: ='All Customers'!B11 -> Clay Ludtke | D11: ='All Customers'!C11 -> 12 | E11: ='All Customers'!D11 -> 28 | F11: ='All Customers'!E11 -> 10880.546 | G11: ='All Customers'!G11 -> 906.71217
C12: Total distinct customers in dataset | D12: =COUNTA('All Customers'!A2:A794) -> 793
C13: Customers tied at the rank-10 cutoff value (Order Count) | D13: =COUNTIF('All Customers'!$C$2:$C$794,D11) -> 18

Sheet All Customers
A1: Customer ID | B1: Customer Name | C1: Order Count | D1: Order Lines | E1: Total Sales | F1: Total Profit | G1: Avg Order Value
A2: EP-13915 | B2: Emily Phan | C2: 17 | D2: 31 | E2: 5478.0608 | F2: 144.9578 | G2: 322.23887
A3: ZC-21910 | B3: Zuschuss Carroll | C3: 13 | D3: 31 | E3: 8025.707 | F3: -1032.149 | G3: 617.36208
A4: JE-15745 | B4: Joel Eaton | C4: 13 | D4: 23 | E4: 6760.815 | F4: 221.7967 | G4: 520.06269
A5: SH-19975 | B5: Sally Hughsby | C5: 13 | D5: 29 | E5: 3406.8395 | F5: 558.474 | G5: 262.06458
A6: CK-12205 | B6: Chloris Kastensmidt | C6: 13 | D6: 32 | E6: 3154.855 | F6: 141.2831 | G6: 242.68115
A7: PG-18820 | B7: Patrick Gardner | C7: 13 | D7: 26 | E7: 3086.907 | F7: 137.4613 | G7: 237.45438
A8: NS-18640 | B8: Noel Staavos | C8: 13 | D8: 26 | E8: 2964.823 | F8: -234.7714 | G8: 228.06331
A9: EA-14035 | B9: Erin Ashbrook | C9: 13 | D9: 25 | E9: 2846.705 | F9: -52.7406 | G9: 218.97731
A10: KL-16645 | B10: Ken Lonsdale | C10: 12 | D10: 29 | E10: 14175.229 | F10: 806.855 | G10: 1181.2691
A11: CL-12565 | B11: Clay Ludtke | C11: 12 | D11: 28 | E11: 10880.546 | F11: 1933.7831 | G11: 906.71217
A12: EH-13765 | B12: Edward Hooks | C12: 12 | D12: 32 | E12: 10310.88 | F12: 1393.5154 | G12: 859.24
A13: PK-19075 | B13: Pete Kriz | C13: 12 | D13: 25 | E13: 8646.934 | F13: 2038.2676 | G13: 720.57783
... A794: LD-16855 | B794: Lela Donovan | C794: 1 | D794: 1 | E794: 5.304 | F794: 0.4641 | G794: 5.304

Sheet Notes
A1: Task 20 - Customer Order Count
A3: Preprocessing
A4: 1. SampleSuperstore.csv has no Order ID or Customer ID column at all. Both were added from a public reference copy of the Superstore dataset, matched row by row and validated on 9 shared columns before trusting the match (same method as Tasks 17 and 19).
A5: 2. Removed 1 exact duplicate row -> 9,993 order lines used.
A6: 3. Key step: one Order ID can span several rows (multiple products bought in one order - 1 to 14 lines, average 2.00). Order Count = COUNT of DISTINCT Order IDs per customer, NOT the number of rows. Counting rows would overstate how often a customer actually orders.
A7: 4. Result: 9,993 order lines collapse to 5,009 distinct orders across 793 distinct customers.
A9: Ties
A10: RANK() gives customers with equal Order Count the same rank and skips the next number. In this dataset, 18 customers are tied at 12 orders for the rank-9/10 cutoff - the 'Top 10 Customers' table shows the strict first 10 rows (tie broken by Total Sales, stated), while 'All Customers' has the full, honest list.
